octokit/__init__.py
octokit/base.py
octokit/errors.py
octokit/utils.py
octokit/webhook.py
octokitpy-0.15.0.dist-info/AUTHORS.rst
octokitpy-0.15.0.dist-info/LICENSE
octokitpy-0.15.0.dist-info/METADATA
octokitpy-0.15.0.dist-info/WHEEL
octokitpy-0.15.0.dist-info/top_level.txt
octokitpy-0.15.0.dist-info/RECORD
