Metadata-Version: 1.1
Name: octokitpy
Version: 0.15.0
Summary: Python client for GitHub API
Home-page: https://github.com/khornberg/octokit.py
Author: Kyle Hornberg
Author-email: kyle.hornberg@gmail.com
License: MIT license
Keywords: github,octokit,api
Platform: UNKNOWN
Classifier: Development Status :: 4 - Beta
Classifier: Intended Audience :: Developers
Classifier: License :: OSI Approved :: MIT License
Classifier: Operating System :: Unix
Classifier: Operating System :: POSIX
Classifier: Operating System :: Microsoft :: Windows
Classifier: Programming Language :: Python
Classifier: Programming Language :: Python :: 3
Classifier: Programming Language :: Python :: 3.6
Classifier: Programming Language :: Python :: 3.7
Classifier: Programming Language :: Python :: 3.8
Classifier: Programming Language :: Python :: Implementation :: CPython
Classifier: Topic :: Utilities
